sam2/__init__.py
sam2/automatic_mask_generator.py
sam2/build_sam.py
sam2/sam2_image_predictor.py
sam2/sam2_video_predictor.py
sam2/configs/__init__.py
sam2/modeling/__init__.py
sam2/modeling/memory_attention.py
sam2/modeling/memory_encoder.py
sam2/modeling/position_encoding.py
sam2/modeling/sam2_base.py
sam2/modeling/sam2_utils.py
sam2/modeling/backbones/__init__.py
sam2/modeling/backbones/hieradet.py
sam2/modeling/backbones/image_encoder.py
sam2/modeling/backbones/utils.py
sam2/modeling/backbones/vitdet.py
sam2/modeling/sam/__init__.py
sam2/modeling/sam/mask_decoder.py
sam2/modeling/sam/prompt_encoder.py
sam2/modeling/sam/transformer.py
sam2/utils/__init__.py
sam2/utils/amg.py
sam2/utils/download.py
sam2/utils/misc.py
sam2/utils/transforms.py
sam2/utils/visualization.py
efficient_track_anything-1.0.dist-info/LICENSE
efficient_track_anything-1.0.dist-info/METADATA
efficient_track_anything-1.0.dist-info/WHEEL
efficient_track_anything-1.0.dist-info/top_level.txt
efficient_track_anything-1.0.dist-info/RECORD
